airqdata/__init__.py
airqdata/influencair.py
airqdata/irceline.py
airqdata/luftdaten.py
airqdata/madavi.py
airqdata/utils.py
airqdata-0.2.dist-info/LICENSE
airqdata-0.2.dist-info/METADATA
airqdata-0.2.dist-info/WHEEL
airqdata-0.2.dist-info/top_level.txt
airqdata-0.2.dist-info/RECORD
