Metadata-Version: 2.1
Name: airqdata
Version: 0.2
Summary: A toolkit to retrieve, analyze and visualize data from a variety of air quality sensors.
Home-page: https://github.com/dr-1/airqdata
Author: Dominik Rubo
License: GNU GPLv3
Keywords: air quality pollution sensor data analysis particulate matter pm influencair irceline luftdaten
Platform: UNKNOWN
Classifier: Development Status :: 3 - Alpha
Classifier: License :: OSI Approved :: GNU General Public License v3 (GPLv3)
Classifier: Operating System :: OS Independent
Classifier: Programming Language :: Python :: 3
Classifier: Programming Language :: Python :: 3.5
Classifier: Programming Language :: Python :: 3.6
Classifier: Programming Language :: Python :: 3.7
Classifier: Topic :: Scientific/Engineering :: Information Analysis
Requires-Python: >=3.5
Requires-Dist: matplotlib (>=2)
Requires-Dist: pandas (>=0.22)
Requires-Dist: requests (>=2.10)
